re_matrix/__init__.py
re_matrix/matrix_math_helpers.py
re_matrix/row_reducer.py
re_matrix-0.1.0.dist-info/METADATA
re_matrix-0.1.0.dist-info/WHEEL
re_matrix-0.1.0.dist-info/top_level.txt
re_matrix-0.1.0.dist-info/RECORD
